ircflags/__init__.py
ircflags/py.typed
ircflags-0.0.1.dist-info/LICENSE
ircflags-0.0.1.dist-info/METADATA
ircflags-0.0.1.dist-info/WHEEL
ircflags-0.0.1.dist-info/top_level.txt
ircflags-0.0.1.dist-info/RECORD
